robodog/__init__.py
robodog/cli.py
unclebulgaria_robodog-2.6.3.dist-info/METADATA
unclebulgaria_robodog-2.6.3.dist-info/WHEEL
unclebulgaria_robodog-2.6.3.dist-info/top_level.txt
unclebulgaria_robodog-2.6.3.dist-info/RECORD
