Metadata-Version: 2.4
Name: unclebulgaria-robodog
Version: 2.6.3
Summary: Robodog
Author-email: adourish <adourish@gmail.com>
Project-URL: Homepage, https://github.com/adourish/robodog
Project-URL: Repository, https://github.com/adourish/robodog.git
Project-URL: Documentation, https://robodog.readthedocs.io
Keywords: robot,dog,automation
Classifier: Programming Language :: Python :: 3
Classifier: License :: OSI Approved :: MIT License
Classifier: Operating System :: OS Independent
Requires-Python: >=3.7
